openpid/__init__.py
openpid/_core.cpython-311-aarch64-linux-gnu.so
openpid/_core.pyi
openpid/pid.py
openpid-0.1.0.dist-info/METADATA
openpid-0.1.0.dist-info/WHEEL
openpid-0.1.0.dist-info/RECORD
openpid-0.1.0.dist-info/licenses/LICENSE
