Metadata-Version: 2.2
Name: openpid
Version: 0.1.0
Summary: PID
Keywords: pid,control,process-control,pybind11,real-time
Author-Email: MAKLE <010makdev@gmail.com>
License: MIT License
Classifier: Programming Language :: Python :: 3
Classifier: Programming Language :: C++
Classifier: License :: OSI Approved :: MIT License
Classifier: Operating System :: OS Independent
Project-URL: Homepage, https://github.com/010Mak/openPID
Requires-Python: >=3.9
Provides-Extra: dev
Requires-Dist: pytest; extra == "dev"
